{
  "title": "Maxpoint",
  "description": "Documentación de sistema de Facturación POS Maxpointde las tiendas de Grupo KFC.",
  "slug": "/category/maxpoint-1",
  "permalink": "/documentacion-DSI/docs/category/maxpoint-1",
  "navigation": {
    "previous": {
      "title": "Manual del Sistema Maxpoint",
      "permalink": "/documentacion-DSI/docs/Maxpoint/Manual del Sistema Maxpoint"
    },
    "next": {
      "title": "Productos",
      "permalink": "/documentacion-DSI/docs/Maxpoint/Productos/"
    }
  }
}