{
  "pluginId": "default",
  "version": "current",
  "label": "Next",
  "banner": null,
  "badge": false,
  "noIndex": false,
  "className": "docs-version-current",
  "isLast": true,
  "docsSidebars": {
    "tutorialSidebar": [
      {
        "type": "link",
        "label": "Tutorial Intro",
        "href": "/documentacion-DSI/docs/intro",
        "docId": "intro",
        "unlisted": false
      },
      {
        "type": "category",
        "label": "Maxpoint",
        "collapsible": true,
        "collapsed": true,
        "items": [
          {
            "type": "link",
            "label": "Manual del Sistema Maxpoint",
            "href": "/documentacion-DSI/docs/Maxpoint/Manual del Sistema Maxpoint",
            "docId": "Maxpoint/Manual del Sistema Maxpoint",
            "unlisted": false
          },
          {
            "type": "category",
            "label": "Kioskos",
            "collapsible": true,
            "collapsed": true,
            "items": [
              {
                "type": "link",
                "label": "Configuración de Políticas Kiosko",
                "href": "/documentacion-DSI/docs/Maxpoint/Kioskos/Descargar Productos y Precios",
                "docId": "Maxpoint/Kioskos/Descargar Productos y Precios",
                "unlisted": false
              }
            ],
            "href": "/documentacion-DSI/docs/category/kioskos"
          },
          {
            "type": "category",
            "label": "Productos",
            "collapsible": true,
            "collapsed": true,
            "items": [
              {
                "type": "link",
                "label": "Productos",
                "href": "/documentacion-DSI/docs/Maxpoint/Productos/Descargar Productos y Precios",
                "docId": "Maxpoint/Productos/Descargar Productos y Precios",
                "unlisted": false
              }
            ],
            "href": "/documentacion-DSI/docs/category/productos"
          },
          {
            "type": "category",
            "label": "Productos",
            "collapsible": true,
            "collapsed": true,
            "items": [
              {
                "type": "link",
                "label": "Restaurante",
                "href": "/documentacion-DSI/docs/Maxpoint/Restaurantes/Descargar Productos y Precios",
                "docId": "Maxpoint/Restaurantes/Descargar Productos y Precios",
                "unlisted": false
              }
            ],
            "href": "/documentacion-DSI/docs/category/productos-1"
          }
        ],
        "href": "/documentacion-DSI/docs/category/maxpoint"
      },
      {
        "type": "category",
        "label": "Tutorial - Basics",
        "collapsible": true,
        "collapsed": true,
        "items": [
          {
            "type": "link",
            "label": "Create a Page",
            "href": "/documentacion-DSI/docs/tutorial-basics/create-a-page",
            "docId": "tutorial-basics/create-a-page",
            "unlisted": false
          },
          {
            "type": "link",
            "label": "Create a Document",
            "href": "/documentacion-DSI/docs/tutorial-basics/create-a-document",
            "docId": "tutorial-basics/create-a-document",
            "unlisted": false
          },
          {
            "type": "link",
            "label": "Create a Blog Post",
            "href": "/documentacion-DSI/docs/tutorial-basics/create-a-blog-post",
            "docId": "tutorial-basics/create-a-blog-post",
            "unlisted": false
          },
          {
            "type": "link",
            "label": "Markdown Features",
            "href": "/documentacion-DSI/docs/tutorial-basics/markdown-features",
            "docId": "tutorial-basics/markdown-features",
            "unlisted": false
          },
          {
            "type": "link",
            "label": "Deploy your site",
            "href": "/documentacion-DSI/docs/tutorial-basics/deploy-your-site",
            "docId": "tutorial-basics/deploy-your-site",
            "unlisted": false
          },
          {
            "type": "link",
            "label": "Congratulations!",
            "href": "/documentacion-DSI/docs/tutorial-basics/congratulations",
            "docId": "tutorial-basics/congratulations",
            "unlisted": false
          }
        ],
        "href": "/documentacion-DSI/docs/category/tutorial---basics"
      },
      {
        "type": "category",
        "label": "Facturación Electronica",
        "collapsible": true,
        "collapsed": true,
        "items": [
          {
            "type": "category",
            "label": "Facturación Electronica",
            "collapsible": true,
            "collapsed": true,
            "items": [
              {
                "type": "link",
                "label": "MANUAL DEL SISTEMA  MAXPOINT",
                "href": "/documentacion-DSI/docs/Facturacion Electronica/Facturacion Electronica copy/MANUAL DEL SISTEMA  MAXPOINT",
                "docId": "Facturacion Electronica/Facturacion Electronica copy/MANUAL DEL SISTEMA  MAXPOINT",
                "unlisted": false
              },
              {
                "type": "link",
                "label": "Maxpoint",
                "href": "/documentacion-DSI/docs/Facturacion Electronica/Facturacion Electronica copy/Maxpoint",
                "docId": "Facturacion Electronica/Facturacion Electronica copy/Maxpoint",
                "unlisted": false
              }
            ],
            "href": "/documentacion-DSI/docs/category/facturación-electronica-1"
          },
          {
            "type": "link",
            "label": "Maxpoint",
            "href": "/documentacion-DSI/docs/Facturacion Electronica/Maxpoint",
            "docId": "Facturacion Electronica/Maxpoint",
            "unlisted": false
          }
        ],
        "href": "/documentacion-DSI/docs/category/facturación-electronica"
      },
      {
        "type": "category",
        "label": "Tutorial - Extras",
        "collapsible": true,
        "collapsed": true,
        "items": [
          {
            "type": "link",
            "label": "Manage Docs Versions",
            "href": "/documentacion-DSI/docs/tutorial-extras/manage-docs-versions",
            "docId": "tutorial-extras/manage-docs-versions",
            "unlisted": false
          },
          {
            "type": "link",
            "label": "Translate your site",
            "href": "/documentacion-DSI/docs/tutorial-extras/translate-your-site",
            "docId": "tutorial-extras/translate-your-site",
            "unlisted": false
          }
        ],
        "href": "/documentacion-DSI/docs/category/tutorial---extras"
      },
      {
        "type": "category",
        "label": "Canales Digitales",
        "collapsible": true,
        "collapsed": true,
        "items": [
          {
            "type": "category",
            "label": "Cupones",
            "collapsible": true,
            "collapsed": true,
            "items": [
              {
                "type": "link",
                "label": "Consumo de API de Cupones",
                "href": "/documentacion-DSI/docs/Canales Digitales/Cupones/Descargar Productos y Precios",
                "docId": "Canales Digitales/Cupones/Descargar Productos y Precios",
                "unlisted": false
              }
            ],
            "href": "/documentacion-DSI/docs/category/cupones"
          },
          {
            "type": "category",
            "label": "SWT-Canales",
            "collapsible": true,
            "collapsed": true,
            "items": [
              {
                "type": "link",
                "label": "Consumo de API de Cupones",
                "href": "/documentacion-DSI/docs/Canales Digitales/SWT - Canales/Descargar Productos y Precios",
                "docId": "Canales Digitales/SWT - Canales/Descargar Productos y Precios",
                "unlisted": false
              },
              {
                "type": "link",
                "label": "Ingreso De Kioscos Para Locales Nuevos",
                "href": "/documentacion-DSI/docs/Canales Digitales/SWT - Canales/Ingreso Kioscos Locales_Nuevos",
                "docId": "Canales Digitales/SWT - Canales/Ingreso Kioscos Locales_Nuevos",
                "unlisted": false
              },
              {
                "type": "link",
                "label": "Debuggear En SQL Server Profiler",
                "href": "/documentacion-DSI/docs/Canales Digitales/SWT - Canales/SQL_Profiler",
                "docId": "Canales Digitales/SWT - Canales/SQL_Profiler",
                "unlisted": false
              },
              {
                "type": "link",
                "label": "Reporte Switch Datafast",
                "href": "/documentacion-DSI/docs/Canales Digitales/SWT - Canales/Switch Datafast",
                "docId": "Canales Digitales/SWT - Canales/Switch Datafast",
                "unlisted": false
              },
              {
                "type": "link",
                "label": "Reporte Switch Kioscos",
                "href": "/documentacion-DSI/docs/Canales Digitales/SWT - Canales/Switch Kioscos",
                "docId": "Canales Digitales/SWT - Canales/Switch Kioscos",
                "unlisted": false
              },
              {
                "type": "link",
                "label": "Switch",
                "href": "/documentacion-DSI/docs/Canales Digitales/SWT - Canales/Switch",
                "docId": "Canales Digitales/SWT - Canales/Switch",
                "unlisted": false
              }
            ],
            "href": "/documentacion-DSI/docs/category/swt-canales"
          },
          {
            "type": "category",
            "label": "Sincronización",
            "collapsible": true,
            "collapsed": true,
            "items": [
              {
                "type": "link",
                "label": "Sincronización Colombia",
                "href": "/documentacion-DSI/docs/Canales Digitales/Sincronizacion/sincronizacion-aranda",
                "docId": "Canales Digitales/Sincronizacion/sincronizacion-aranda",
                "unlisted": false
              },
              {
                "type": "link",
                "label": "Sincronización Creación En Aranda",
                "href": "/documentacion-DSI/docs/Canales Digitales/Sincronizacion/sincronizacion-aranda copy",
                "docId": "Canales Digitales/Sincronizacion/sincronizacion-aranda copy",
                "unlisted": false
              }
            ],
            "href": "/documentacion-DSI/docs/category/sincronización"
          }
        ]
      }
    ]
  },
  "docs": {
    "Canales Digitales/Cupones/Descargar Productos y Precios": {
      "id": "Canales Digitales/Cupones/Descargar Productos y Precios",
      "title": "Consumo de API de Cupones",
      "description": "Para consumir la API de cupones, utilizamos las siguientes herramientas:",
      "sidebar": "tutorialSidebar"
    },
    "Canales Digitales/Sincronizacion/sincronizacion-aranda": {
      "id": "Canales Digitales/Sincronizacion/sincronizacion-aranda",
      "title": "Sincronización Colombia",
      "description": "Manual de Usuario - Sistema 2023 - Soporte App",
      "sidebar": "tutorialSidebar"
    },
    "Canales Digitales/Sincronizacion/sincronizacion-aranda copy": {
      "id": "Canales Digitales/Sincronizacion/sincronizacion-aranda copy",
      "title": "Sincronización Creación En Aranda",
      "description": "Manual de Usuario - Sistema 2023 - Soporte App",
      "sidebar": "tutorialSidebar"
    },
    "Canales Digitales/SWT - Canales/Descargar Productos y Precios": {
      "id": "Canales Digitales/SWT - Canales/Descargar Productos y Precios",
      "title": "Consumo de API de Cupones",
      "description": "Prueba",
      "sidebar": "tutorialSidebar"
    },
    "Canales Digitales/SWT - Canales/Ingreso Kioscos Locales_Nuevos": {
      "id": "Canales Digitales/SWT - Canales/Ingreso Kioscos Locales_Nuevos",
      "title": "Ingreso De Kioscos Para Locales Nuevos",
      "description": "Contenido",
      "sidebar": "tutorialSidebar"
    },
    "Canales Digitales/SWT - Canales/SQL_Profiler": {
      "id": "Canales Digitales/SWT - Canales/SQL_Profiler",
      "title": "Debuggear En SQL Server Profiler",
      "description": "Al ser una soporte de canales digitales, nos encargamos de verificar el canal de domicilio y el de kiosco.",
      "sidebar": "tutorialSidebar"
    },
    "Canales Digitales/SWT - Canales/Switch": {
      "id": "Canales Digitales/SWT - Canales/Switch",
      "title": "Switch",
      "description": "Antecedentes",
      "sidebar": "tutorialSidebar"
    },
    "Canales Digitales/SWT - Canales/Switch Datafast": {
      "id": "Canales Digitales/SWT - Canales/Switch Datafast",
      "title": "Reporte Switch Datafast",
      "description": "Desarrollo",
      "sidebar": "tutorialSidebar"
    },
    "Canales Digitales/SWT - Canales/Switch Kioscos": {
      "id": "Canales Digitales/SWT - Canales/Switch Kioscos",
      "title": "Reporte Switch Kioscos",
      "description": "Antecedentes",
      "sidebar": "tutorialSidebar"
    },
    "Facturacion Electronica/Facturacion Electronica copy/MANUAL DEL SISTEMA  MAXPOINT": {
      "id": "Facturacion Electronica/Facturacion Electronica copy/MANUAL DEL SISTEMA  MAXPOINT",
      "title": "MANUAL DEL SISTEMA  MAXPOINT",
      "description": "Manual para productos, restaurantes, reportes, general, seguridades, depósitos y cadena.",
      "sidebar": "tutorialSidebar"
    },
    "Facturacion Electronica/Facturacion Electronica copy/Maxpoint": {
      "id": "Facturacion Electronica/Facturacion Electronica copy/Maxpoint",
      "title": "Maxpoint",
      "description": "first Docusaurus document!",
      "sidebar": "tutorialSidebar"
    },
    "Facturacion Electronica/Maxpoint": {
      "id": "Facturacion Electronica/Maxpoint",
      "title": "Maxpoint",
      "description": "first Docusaurus document!",
      "sidebar": "tutorialSidebar"
    },
    "intro": {
      "id": "intro",
      "title": "Tutorial Intro",
      "description": "Let's discover Docusaurus in less than 5 minutes.",
      "sidebar": "tutorialSidebar"
    },
    "Maxpoint/Kioskos/Descargar Productos y Precios": {
      "id": "Maxpoint/Kioskos/Descargar Productos y Precios",
      "title": "Configuración de Políticas Kiosko",
      "description": "Introducción - En este manual se detalla las configuraciones de las políticas que se deben configurar en el BackOffice de Max-Point para el correcto funcionamiento de Kiosko.",
      "sidebar": "tutorialSidebar"
    },
    "Maxpoint/Manual del Sistema Maxpoint": {
      "id": "Maxpoint/Manual del Sistema Maxpoint",
      "title": "Manual del Sistema Maxpoint",
      "description": "Manual para productos, restaurantes, reportes, general, seguridades, depósitos y cadena.",
      "sidebar": "tutorialSidebar"
    },
    "Maxpoint/Productos/Descargar Productos y Precios": {
      "id": "Maxpoint/Productos/Descargar Productos y Precios",
      "title": "Productos",
      "description": "1.\tProductos",
      "sidebar": "tutorialSidebar"
    },
    "Maxpoint/Restaurantes/Descargar Productos y Precios": {
      "id": "Maxpoint/Restaurantes/Descargar Productos y Precios",
      "title": "Restaurante",
      "description": "",
      "sidebar": "tutorialSidebar"
    },
    "tutorial-basics/congratulations": {
      "id": "tutorial-basics/congratulations",
      "title": "Congratulations!",
      "description": "You have just learned the basics of Docusaurus and made some changes to the initial template.",
      "sidebar": "tutorialSidebar"
    },
    "tutorial-basics/create-a-blog-post": {
      "id": "tutorial-basics/create-a-blog-post",
      "title": "Create a Blog Post",
      "description": "Docusaurus creates a page for each blog post, but also a blog index page, a tag system, an RSS feed...",
      "sidebar": "tutorialSidebar"
    },
    "tutorial-basics/create-a-document": {
      "id": "tutorial-basics/create-a-document",
      "title": "Create a Document",
      "description": "Documents are groups of pages connected through:",
      "sidebar": "tutorialSidebar"
    },
    "tutorial-basics/create-a-page": {
      "id": "tutorial-basics/create-a-page",
      "title": "Create a Page",
      "description": "Add Markdown or React files to src/pages to create a standalone page:",
      "sidebar": "tutorialSidebar"
    },
    "tutorial-basics/deploy-your-site": {
      "id": "tutorial-basics/deploy-your-site",
      "title": "Deploy your site",
      "description": "Docusaurus is a static-site-generator (also called Jamstack).",
      "sidebar": "tutorialSidebar"
    },
    "tutorial-basics/markdown-features": {
      "id": "tutorial-basics/markdown-features",
      "title": "Markdown Features",
      "description": "Docusaurus supports Markdown and a few additional features.",
      "sidebar": "tutorialSidebar"
    },
    "tutorial-extras/manage-docs-versions": {
      "id": "tutorial-extras/manage-docs-versions",
      "title": "Manage Docs Versions",
      "description": "Docusaurus can manage multiple versions of your docs.",
      "sidebar": "tutorialSidebar"
    },
    "tutorial-extras/translate-your-site": {
      "id": "tutorial-extras/translate-your-site",
      "title": "Translate your site",
      "description": "Let's translate docs/intro.md to French.",
      "sidebar": "tutorialSidebar"
    }
  }
}